LICENSE
MANIFEST.in
README.rst
setup.py
docs/Makefile
docs/conf.py
docs/eleven.rst
docs/index.rst
docs/make.bat
docs/_build/.DS_Store
docs/_build/doctrees/eleven.doctree
docs/_build/doctrees/environment.pickle
docs/_build/doctrees/index.doctree
docs/_build/singlehtml/.buildinfo
docs/_build/singlehtml/index.html
docs/_build/singlehtml/objects.inv
docs/_build/singlehtml/.doctrees/eleven.doctree
docs/_build/singlehtml/.doctrees/environment.pickle
docs/_build/singlehtml/.doctrees/index.doctree
docs/_build/singlehtml/_static/ajax-loader.gif
docs/_build/singlehtml/_static/basic.css
docs/_build/singlehtml/_static/comment-bright.png
docs/_build/singlehtml/_static/comment-close.png
docs/_build/singlehtml/_static/comment.png
docs/_build/singlehtml/_static/default.css
docs/_build/singlehtml/_static/doctools.js
docs/_build/singlehtml/_static/down-pressed.png
docs/_build/singlehtml/_static/down.png
docs/_build/singlehtml/_static/eleven.jpg
docs/_build/singlehtml/_static/file.png
docs/_build/singlehtml/_static/jquery.js
docs/_build/singlehtml/_static/minus.png
docs/_build/singlehtml/_static/plus.png
docs/_build/singlehtml/_static/pygments.css
docs/_build/singlehtml/_static/searchtools.js
docs/_build/singlehtml/_static/sidebar.js
docs/_build/singlehtml/_static/underscore.js
docs/_build/singlehtml/_static/up-pressed.png
docs/_build/singlehtml/_static/up.png
docs/_build/singlehtml/_static/websupport.js
docs/_static/eleven.jpg
eleven/__init__.py
eleven/eleven.py
eleven/test_eleven.py
eleven.egg-info/PKG-INFO
eleven.egg-info/SOURCES.txt
eleven.egg-info/dependency_links.txt
eleven.egg-info/requires.txt
eleven.egg-info/top_level.txt
eleven/test/vandesompele-2002-cq.txt