Metadata-Version: 1.1
Name: eleven
Version: 0.1
Summary: A friendly implementation of the GeNorm multi-gene RT-qPCR normalization algorithm
Home-page: http://github.com/tdsmith/eleven/
Author: Tim D. Smith
Author-email: eleven@tim-smith.us
License: BSD
Platform: any
Classifier: Development Status :: 4 - Beta
Classifier: Intended Audience :: Science/Research
Classifier: License :: OSI Approved :: BSD License
Classifier: Natural Language :: English
Classifier: Operating System :: OS Independent
Classifier: Topic :: Scientific/Engineering :: Bio-Informatics
Classifier: Topic :: Software Development :: Libraries :: Python Modules
Classifier: Programming Language :: Python
Classifier: Programming Language :: Python :: 2.7
